openai_simple_embeddings/__init__.py
openai_simple_embeddings/base.py
openai_simple_embeddings/langchain_embeddings.py
openai_simple_embeddings/settings.py
openai_simple_embeddings-0.1.2.dist-info/LICENSE
openai_simple_embeddings-0.1.2.dist-info/METADATA
openai_simple_embeddings-0.1.2.dist-info/WHEEL
openai_simple_embeddings-0.1.2.dist-info/top_level.txt
openai_simple_embeddings-0.1.2.dist-info/RECORD
