Metadata-Version: 2.2
Name: openai-simple-embeddings
Version: 0.1.2
Summary: 基于OPENAI兼容API接口的embeddings服务封装，以解决langchain_community.vectorstores在使用bge-m3/bge-reranker-v2-m3等模型提供的OPENAI兼容API接口服务时遇到的兼容性问题。
Author: rRR0VrFP
Maintainer: rRR0VrFP
License: Apache License, Version 2.0
Keywords: openai-simple-embeddings
Classifier: Development Status :: 5 - Production/Stable
Classifier: Intended Audience :: Developers
Classifier: Topic :: Software Development :: Libraries :: Python Modules
Classifier: License :: OSI Approved :: Apache Software License
Classifier: Programming Language :: Python :: 3
Classifier: Programming Language :: Python :: 3 :: Only
License-File: LICENSE
Requires-Dist: openai
Requires-Dist: langchain-core
Requires-Dist: python-environment-settings
Dynamic: author
Dynamic: classifier
Dynamic: description
Dynamic: description-content-type
Dynamic: keywords
Dynamic: license
Dynamic: maintainer
Dynamic: requires-dist
Dynamic: summary
